{
    "Id": "physics.subatomic_particle_composition",
    "Name": "Subatomic particle composition",
    "Description": "A CVT which denotes the number of one type of fundamental particle which make up a compound subatomic particle.",
    "Mediator": true,
    "ExpectedTypes": null,
    "Enumerated": false,
    "Properties": [
        {
            "Id": "physics.subatomic_particle_composition.number",
            "Name": "Number",
            "Description": "How many of this particle are used",
            "ObjectType": "type.int",
            "Unique": true,
            "Required": true
        },
        {
            "Id": "physics.subatomic_particle_composition.particle",
            "Name": "Particle",
            "Description": "A subatomic particle which makes up a compound particle",
            "ObjectType": "physics.quark",
            "Unique": true,
            "Required": true
        }
    ]
}