{
    "Sid": "computer.internet_protocol",
    "Name": "Internet Protocol",
    "Description": "The Internet Protocol (IP) is the principal communications protocol used for relaying datagrams (packets) across an internetwork using the Internet Protocol Suite. This type captures the various forms of IP used by devices and programs communicating over some sort of network.",
    "Mediator": false,
    "ExpectedTypes": [
        "common.topic"
    ],
    "Enumerated": false,
    "Properties": null
}